e2edutch/__init__.py
e2edutch/__version__.py
e2edutch/bert.py
e2edutch/conll.py
e2edutch/coref_kernels.so
e2edutch/coref_model.py
e2edutch/coref_ops.py
e2edutch/download.py
e2edutch/metrics.py
e2edutch/minimize.py
e2edutch/naf.py
e2edutch/predict.py
e2edutch/stanza.py
e2edutch/train.py
e2edutch/util.py
e2edutch/cfg/defaults.conf
e2edutch/cfg/models.conf
e2edutch/cfg/test.conf
test/__init__.py
test/test_bert.py
test/test_conll.py
test/test_coref_model.py
test/test_metrics.py
test/test_minimize.py
test/test_predict.py
test/test_stanza.py
test/test_util.py
e2e_Dutch-0.4.1.dist-info/LICENSE
e2e_Dutch-0.4.1.dist-info/METADATA
e2e_Dutch-0.4.1.dist-info/WHEEL
e2e_Dutch-0.4.1.dist-info/top_level.txt
e2e_Dutch-0.4.1.dist-info/RECORD
