Metadata-Version: 2.1
Name: e2e-Dutch
Version: 0.4.1
Summary: Coreference resolution with e2e for Dutch
Home-page: https://github.com/Filter-Bubble/e2e-Dutch
Author: Dafne van Kuppevelt
Author-email: d.vankuppevelt@esciencecenter.nl
License: UNKNOWN
Platform: UNKNOWN
Classifier: Programming Language :: Python :: 3
Classifier: Development Status :: 4 - Beta
Classifier: Environment :: Console
Classifier: License :: OSI Approved :: Apache Software License
Classifier: Operating System :: OS Independent
Requires-Python: >=3.6
License-File: LICENSE
Requires-Dist: tensorflow (>=2.0.0)
Requires-Dist: h5py
Requires-Dist: pyhocon
Requires-Dist: scipy
Requires-Dist: scikit-learn
Requires-Dist: torch (<=1.7.1)
Requires-Dist: transformers (<=3.5.1)
Requires-Dist: KafNafParserPy
Requires-Dist: stanza
Provides-Extra: doc
Requires-Dist: sphinx ; extra == 'doc'
Requires-Dist: m2r2 ; extra == 'doc'
